{
  "NIH_IOM": {
    "SODIUM_NA": {
      "MALE": {
        "14-150": {
          "rdi": 1500,
          "ul": 2300
        }
      },
      "FEMALE": {
        "14-150": {
          "rdi": 1500,
          "ul": 2300
        }
      },
      "FEMALE_PREGNANT": {
        "14-50": {
          "rdi": 1500,
          "ul": 2300
        }
      },
      "FEMALE_LACTATING": {
        "14-50": {
          "rdi": 1500,
          "ul": 2300
        }
      }
    },
    "POTASSIUM_K": {
      "MALE": {
        "14-150": {
          "rdi": 4700,
          "ul": null
        }
      },
      "FEMALE": {
        "14-150": {
          "rdi": 4700,
          "ul": null
        }
      },
      "FEMALE_PREGNANT": {
        "14-50": {
          "rdi": 4700,
          "ul": null
        }
      },
      "FEMALE_LACTATING": {
        "14-50": {
          "rdi": 4700,
          "ul": null
        }
      }
    },
    "MAGNESIUM_MG": {
      "MALE": {
        "19-150": {
          "rdi": 500,
          "ul": 350
        }
      },
      "FEMALE": {
        "19-150": {
          "rdi": 400,
          "ul": 350
        }
      },
      "FEMALE_PREGNANT": {
        "14-50": {
          "rdi": 450,
          "ul": 350
        }
      },
      "FEMALE_LACTATING": {
        "14-50": {
          "rdi": 400,
          "ul": 350
        }
      }
    },
    "CALCIUM_CA": {
      "MALE": {
        "19-150": {
          "rdi": 1200,
          "ul": 2500
        }
      },
      "FEMALE": {
        "19-150": {
          "rdi": 1200,
          "ul": 2500
        }
      },
      "FEMALE_PREGNANT": {
        "14-50": {
          "rdi": 1200,
          "ul": 2500
        }
      },
      "FEMALE_LACTATING": {
        "14-50": {
          "rdi": 1200,
          "ul": 2500
        }
      }
    }
  },
  "WHO_FAO": {
    "SODIUM_NA": {
      "ALL": {
        "14-150": {
          "rdi": 1500,
          "ul": 2000
        }
      }
    },
    "POTASSIUM_K": {
      "ALL": {
        "14-150": {
          "rdi": 4700,
          "ul": null
        }
      }
    }
  },
  "EFSA": {},
  "UK_SACN": {},
  "DACH": {},
  "SPORTS": {}
}
